README.txt
setup.cfg
setup.py
Products/__init__.py
Products.IMS.egg-info/PKG-INFO
Products.IMS.egg-info/SOURCES.txt
Products.IMS.egg-info/dependency_links.txt
Products.IMS.egg-info/entry_points.txt
Products.IMS.egg-info/namespace_packages.txt
Products.IMS.egg-info/not-zip-safe
Products.IMS.egg-info/requires.txt
Products.IMS.egg-info/top_level.txt
Products/IMS/__init__.py
Products/IMS/adapter.py
Products/IMS/config.py
Products/IMS/configure.zcml
Products/IMS/events.py
Products/IMS/interfaces.py
Products/IMS/permissions.zcml
Products/IMS/setuphandlers.py
Products/IMS/utils.py
Products/IMS/browser/__init__.py
Products/IMS/browser/configure.zcml
Products/IMS/browser/viewlets.py
Products/IMS/browser/views.py
Products/IMS/browser/vocabulary.py
Products/IMS/browser/images/message_forward.gif
Products/IMS/browser/images/message_forwarded.gif
Products/IMS/browser/images/message_icon.gif
Products/IMS/browser/images/message_read_icon.gif
Products/IMS/browser/images/message_replied.gif
Products/IMS/browser/images/message_reply.gif
Products/IMS/browser/images/receivedmessagefolder_icon.gif
Products/IMS/browser/images/sentmessagefolder_icon.gif
Products/IMS/browser/templates/ims_bar.pt
Products/IMS/browser/templates/message.pt
Products/IMS/browser/templates/message_folder.pt
Products/IMS/browser/templates/message_form.pt
Products/IMS/browser/templates/message_macros.pt
Products/IMS/browser/templates/messages_delete.pt
Products/IMS/content/__init__.py
Products/IMS/content/message.py
Products/IMS/content/message_folder.py
Products/IMS/i18n/IMS-de-plone.po
Products/IMS/i18n/IMS-de.po
Products/IMS/profiles/default/actionicons.xml
Products/IMS/profiles/default/actions.xml
Products/IMS/profiles/default/catalog.xml
Products/IMS/profiles/default/cssregistry.xml
Products/IMS/profiles/default/import_steps.xml
Products/IMS/profiles/default/ims_various.txt
Products/IMS/profiles/default/metadata.xml
Products/IMS/profiles/default/propertiestool.xml
Products/IMS/profiles/default/rolemap.xml
Products/IMS/profiles/default/skins.xml
Products/IMS/profiles/default/types.xml
Products/IMS/profiles/default/viewlets.xml
Products/IMS/profiles/default/workflows.xml
Products/IMS/profiles/default/types/Message.xml
Products/IMS/profiles/default/types/ReceivedMessageFolder.xml
