Metadata-Version: 1.0
Name: Products.IMS
Version: 0.1
Summary: Internal messaging system
Home-page: http://plone.org/products/ims
Author: Raptus AG
Author-email: skaeser@raptus.com
License: GPL
Keywords: Plone Messaging
Platform: UNKNOWN
Classifier: Programming Language :: Python
Classifier: Topic :: Software Development :: Libraries :: Python Modules
